LICENSE
MANIFEST.in
README.rst
setup.py
acdh_spacyal.egg-info/PKG-INFO
acdh_spacyal.egg-info/SOURCES.txt
acdh_spacyal.egg-info/dependency_links.txt
acdh_spacyal.egg-info/requires.txt
acdh_spacyal.egg-info/top_level.txt
spacyal/__init__.py
spacyal/admin.py
spacyal/api_urls.py
spacyal/api_views.py
spacyal/apps.py
spacyal/models.py
spacyal/tables.py
spacyal/tasks.py
spacyal/urls.py
spacyal/views.py
spacyal/migrations/0001_initial.py
spacyal/migrations/0002_auto_20180408_1343.py
spacyal/migrations/0003_auto_20180410_1115.py
spacyal/migrations/0004_al_project_users_allowed.py
spacyal/migrations/0005_auto_20180410_1508.py
spacyal/migrations/0006_auto_20180426_1356.py
spacyal/migrations/0007_auto_20180802_1332.py
spacyal/migrations/__init__.py
spacyal/static/spacyal/css/spacyal.css
spacyal/static/spacyal/js/csrf.js
spacyal/static/spacyal/js/package-lock.json
spacyal/static/spacyal/js/package.json
spacyal/templates/spacyal/al_project.html
spacyal/templates/spacyal/al_project_list.html