Metadata-Version: 1.1
Name: acdh-spacyal
Version: 0.3.6
Summary: Addon to Django apps that allows to retrain Spacy NER with active learning.
Home-page: https://github.com/sennierer/spacyal
Author: Matthias Schlögl
Author-email: matthias.schloegl@oeaw.ac.at
License: MIT License
Platform: UNKNOWN
Classifier: Development Status :: 4 - Beta
Classifier: Environment :: Web Environment
Classifier: Framework :: Django
Classifier: Framework :: Django :: 2.0
Classifier: Intended Audience :: Developers
Classifier: License :: OSI Approved :: MIT License
Classifier: Operating System :: OS Independent
Classifier: Programming Language :: Python
Classifier: Programming Language :: Python :: 3.4
Classifier: Programming Language :: Python :: 3.5
Classifier: Programming Language :: Python :: 3.6
Classifier: Topic :: Internet :: WWW/HTTP
Classifier: Topic :: Internet :: WWW/HTTP :: Dynamic Content
